now_playing/__init__.py
now_playing/api.py
now_playing/cli.py
now_playing/config.py
now_playing/display.py
now_playing_cli-2.0.0.dist-info/METADATA
now_playing_cli-2.0.0.dist-info/WHEEL
now_playing_cli-2.0.0.dist-info/entry_points.txt
now_playing_cli-2.0.0.dist-info/RECORD
