Metadata-Version: 2.4
Name: now-playing-cli
Version: 2.0.0
Summary: CLI tool to monitor Plex activity via Tautulli API
Project-URL: Homepage, https://github.com/dangerouslaser/now-playing-cli
Project-URL: Repository, https://github.com/dangerouslaser/now-playing-cli
Project-URL: Issues, https://github.com/dangerouslaser/now-playing-cli/issues
Author: dangerouslaser
License-Expression: MIT
Keywords: cli,media,plex,streaming,tautulli
Classifier: Development Status :: 4 - Beta
Classifier: Environment :: Console
Classifier: Intended Audience :: End Users/Desktop
Classifier: License :: OSI Approved :: MIT License
Classifier: Operating System :: OS Independent
Classifier: Programming Language :: Python :: 3
Classifier: Programming Language :: Python :: 3.9
Classifier: Programming Language :: Python :: 3.10
Classifier: Programming Language :: Python :: 3.11
Classifier: Programming Language :: Python :: 3.12
Classifier: Topic :: Multimedia :: Video
Requires-Python: >=3.9
Requires-Dist: httpx>=0.25.0
Requires-Dist: rich>=13.0.0
Requires-Dist: typer>=0.9.0
Provides-Extra: keyring
Requires-Dist: keyring>=24.0.0; extra == 'keyring'
